structlog/__init__.py
structlog/_base.py
structlog/_config.py
structlog/_frames.py
structlog/_generic.py
structlog/_greenlets.py
structlog/_log_levels.py
structlog/_native.py
structlog/_output.py
structlog/_utils.py
structlog/contextvars.py
structlog/dev.py
structlog/exceptions.py
structlog/processors.py
structlog/py.typed
structlog/stdlib.py
structlog/testing.py
structlog/threadlocal.py
structlog/tracebacks.py
structlog/twisted.py
structlog/types.py
structlog/typing.py
structlog-24.3.0.dist-info/METADATA
structlog-24.3.0.dist-info/WHEEL
structlog-24.3.0.dist-info/licenses/LICENSE-APACHE
structlog-24.3.0.dist-info/licenses/LICENSE-MIT
structlog-24.3.0.dist-info/licenses/NOTICE
structlog-24.3.0.dist-info/RECORD
